CHANGELOG
LICENSE
MANIFEST.in
README.md
setup.py
doc/en/index.md
examples/basic.py
examples/group.py
examples/inherit.py
ptest/__init__.py
ptest/assertion.py
ptest/config.py
ptest/decorator.py
ptest/enumeration.py
ptest/exception.py
ptest/main.py
ptest/plistener.py
ptest/plogger.py
ptest/reporter.py
ptest/screen_capturer.py
ptest/test_executor.py
ptest/test_filter.py
ptest/test_finder.py
ptest/test_suite.py
ptest/util.py
ptest.egg-info/PKG-INFO
ptest.egg-info/SOURCES.txt
ptest.egg-info/dependency_links.txt
ptest.egg-info/entry_points.txt
ptest.egg-info/not-zip-safe
ptest.egg-info/top_level.txt
ptest/htmltemplate/index.html
ptest/htmltemplate/report.css
ptest/htmltemplate/report.js