Metadata-Version: 1.1
Name: ptest
Version: 1.9.2
Summary: light test framework for Python
Home-page: https://github.com/KarlGong/ptest
Author: Karl Gong
Author-email: karl.gong@outlook.com
License: Apache
Keywords: test testing framework automation python runner
Platform: UNKNOWN
Classifier: License :: OSI Approved :: Apache Software License
Classifier: Topic :: Software Development :: Testing
Classifier: Operating System :: Microsoft :: Windows
Classifier: Operating System :: MacOS :: MacOS X
Classifier: Programming Language :: Python :: 2.7
Classifier: Programming Language :: Python :: 3.4
Classifier: Programming Language :: Python :: 3.5
Classifier: Programming Language :: Python :: 3.6
